{"assets/fonts/Lato-Bold.ttf":["assets/fonts/Lato-Bold.ttf"],"assets/fonts/Lato-Regular.ttf":["assets/fonts/Lato-Regular.ttf"],"assets/images/ODE.png":["assets/images/ODE.png"],"assets/images/call.png":["assets/images/call.png"],"assets/images/chalo.png":["assets/images/chalo.png"],"assets/images/facebook.png":["assets/images/facebook.png"],"assets/images/github.png":["assets/images/github.png"],"assets/images/gmail.png":["assets/images/gmail.png"],"assets/images/htm.png":["assets/images/htm.png"],"assets/images/ic_catholicsg_church_app.png":["assets/images/ic_catholicsg_church_app.png"],"assets/images/ic_play_store.png":["assets/images/ic_play_store.png"],"assets/images/linkedin.png":["assets/images/linkedin.png"],"assets/images/message.png":["assets/images/message.png"],"assets/images/ninoxdb.png":["assets/images/ninoxdb.png"],"assets/images/profile_pic.png":["assets/images/profile_pic.png"],"assets/images/resume.pdf":["assets/images/resume.pdf"],"packages/cupertino_icons/assets/CupertinoIcons.ttf":["packages/cupertino_icons/assets/CupertinoIcons.ttf"]}